README.md
setup.py
edecs/__init__.py
edecs.egg-info/PKG-INFO
edecs.egg-info/SOURCES.txt
edecs.egg-info/dependency_links.txt
edecs.egg-info/not-zip-safe
edecs.egg-info/top_level.txt
edecs/models/__init__.py
edecs/models/component.py
edecs/models/entity.py
edecs/models/event.py
edecs/models/exceptions.py
edecs/models/message.py
edecs/models/system.py
edecs/models/world.py