Metadata-Version: 1.0
Name: edecs
Version: 1.0.6
Summary: Event-driven Entity-Component-System engine
Home-page: UNKNOWN
Author: UNKNOWN
Author-email: dovakin121212@gmail.com
License: UNKNOWN
Platform: UNKNOWN
